qupy/__init__.py
qupy/operator.py
qupy/qubit.py
qupy-1.1.1.dist-info/METADATA
qupy-1.1.1.dist-info/RECORD
qupy-1.1.1.dist-info/WHEEL
qupy-1.1.1.dist-info/top_level.txt
