Metadata-Version: 2.1
Name: qupy
Version: 1.1.1
Summary: QuPy: A quantum circuit simulator for both CPU and GPU
Home-page: https://github.com/ken-nakanishi/qupy
Author: Ken Nakanishi
Author-email: ikyhn1.ken.n@gmail.com
License: MIT License
Requires-Dist: numpy
